sleepytime/__init__.py
sleepytime/__main__.py
sleepytime/__version__.py
sleepytime/exceptions.py
sleepytime/log.py
sleepytime/mouse_watcher.py
sleepytime/resume_watcher.py
sleepytime/window.py
sleepytime-0.1.5.dist-info/LICENSE
sleepytime-0.1.5.dist-info/METADATA
sleepytime-0.1.5.dist-info/WHEEL
sleepytime-0.1.5.dist-info/top_level.txt
sleepytime-0.1.5.dist-info/RECORD
