Metadata-Version: 2.1
Name: sleepytime
Version: 0.1.5
Home-page: http://github.com/csm10495/sleepytime
Author: csm10495
Author-email: csm10495@gmail.com
License: MIT License
Classifier: Intended Audience :: Developers
Classifier: Natural Language :: English
Classifier: Operating System :: Microsoft :: Windows
Classifier: Programming Language :: Python
Classifier: Programming Language :: Python :: 3
Requires-Python: >=3.10
License-File: LICENSE
Requires-Dist: PySimpleGUI-4-foss
Requires-Dist: psgtray-foss
Requires-Dist: pywin32
Requires-Dist: tendo
Requires-Dist: pyautogui
Requires-Dist: appdirs
